{"@module": "cgcnn.material", "@class": "Material", "@version": null, "formula": "Ca3CdO4", "structure": {"@module": "pymatgen.core.structure", "@class": "Structure", "charge": 0, "lattice": {"matrix": [[3.3390501248432383, -4.746377728336795, 0.0], [3.3390501248432383, 4.746377728336795, 0.0], [0.0, 0.0, 3.369540174669177]], "pbc": [true, true, true], "a": 5.803219561266591, "b": 5.803219561266591, "c": 3.369540174669177, "alpha": 90.0, "beta": 90.0, "gamma": 109.7476568756738, "volume": 106.80359482119732}, "properties": {}, "sites": [{"species": [{"element": "Ca", "occu": 1}], "abc": [0.5, 0.5, 0.0], "properties": {}, "label": "Ca", "xyz": [3.3390501248432383, 0.0, 0.0]}, {"species": [{"element": "Ca", "occu": 1}], "abc": [0.0, 0.5, 0.5], "properties": {}, "label": "Ca", "xyz": [1.6695250624216191, 2.3731888641683976, 1.6847700873345886]}, {"species": [{"element": "Ca", "occu": 1}], "abc": [0.5, 0.0, 0.5], "properties": {}, "label": "Ca", "xyz": [1.6695250624216191, -2.3731888641683976, 1.6847700873345886]}, {"species": [{"element": "Cd", "occu": 1}], "abc": [0.0, 0.0, 0.0], "properties": {}, "label": "Cd", "xyz": [0.0, 0.0, 0.0]}, {"species": [{"element": "O", "occu": 1}], "abc": [0.2537290345120624, 0.7462709654879376, 0.0], "properties": {}, "label": "O", "xyz": [3.3390501248432383, 2.337790051455893, 0.0]}, {"species": [{"element": "O", "occu": 1}], "abc": [0.7462497755775175, 0.7462497755775175, 0.5], "properties": {}, "label": "O", "xyz": [4.983530812612696, 0.0, 1.6847700873345886]}, {"species": [{"element": "O", "occu": 1}], "abc": [0.2537502244224825, 0.2537502244224825, 0.5], "properties": {}, "label": "O", "xyz": [1.69456943707378, 0.0, 1.6847700873345886]}, {"species": [{"element": "O", "occu": 1}], "abc": [0.7462709654879376, 0.2537290345120624, 0.0], "properties": {}, "label": "O", "xyz": [3.3390501248432383, -2.337790051455893, 0.0]}]}, "target_site_names": ["O1", "O2"], "target_site_indices": [4, 5], "target_vals": [-1.5645000000000047, -1.3628000000000022], "charges": [0, 0]}