{"@module": "cgcnn.material", "@class": "Material", "@version": null, "formula": "Sr2TiO4", "structure": {"@module": "pymatgen.core.structure", "@class": "Structure", "charge": 0, "lattice": {"matrix": [[-1.9450952669196113, 1.9450952669196113, 6.255311704266708], [1.9450952669196113, -1.9450952669196113, 6.255311704266708], [1.9450952669196113, 1.9450952669196113, -6.255311704266708]], "pbc": [true, true, true], "a": 6.833426352301034, "b": 6.833426352301034, "c": 6.833426352301034, "alpha": 146.92483465288097, "beta": 146.92483465288097, "gamma": 47.47508967390185, "volume": 94.66527504897611}, "properties": {}, "sites": [{"species": [{"element": "Sr", "occu": 1}], "abc": [0.644833644333545, 0.644833644333545, 0.0], "properties": {}, "label": "Sr", "xyz": [0.0, 0.0, 8.067270885409158]}, {"species": [{"element": "Sr", "occu": 1}], "abc": [0.355166355666455, 0.355166355666455, 0.0], "properties": {}, "label": "Sr", "xyz": [0.0, 0.0, 4.443352523124257]}, {"species": [{"element": "Ti", "occu": 1}], "abc": [0.0, 0.0, 0.0], "properties": {}, "label": "Ti", "xyz": [0.0, 0.0, 0.0]}, {"species": [{"element": "O", "occu": 1}], "abc": [0.8409574018396597, 0.8409574018396597, 0.0], "properties": {}, "label": "O", "xyz": [0.0, 0.0, 10.520901357034688]}, {"species": [{"element": "O", "occu": 1}], "abc": [0.1590425981603403, 0.1590425981603403, 0.0], "properties": {}, "label": "O", "xyz": [0.0, 0.0, 1.989722051498727]}, {"species": [{"element": "O", "occu": 1}], "abc": [0.5, 0.0, 0.5], "properties": {}, "label": "O", "xyz": [0.0, 1.9450952669196113, 0.0]}, {"species": [{"element": "O", "occu": 1}], "abc": [0.0, 0.5, 0.5], "properties": {}, "label": "O", "xyz": [1.9450952669196113, 0.0, 0.0]}]}, "target_site_names": ["O1", "O2"], "target_site_indices": [3, 5], "target_vals": [1.2045245356825585, -0.28501490678847796], "charges": [2, 2]}